README.md
setup.cfg
setup.py
drf_irelation/__init__.py
drf_irelation/irelation.py
drf_irelation.egg-info/PKG-INFO
drf_irelation.egg-info/SOURCES.txt
drf_irelation.egg-info/dependency_links.txt
drf_irelation.egg-info/not-zip-safe
drf_irelation.egg-info/requires.txt
drf_irelation.egg-info/top_level.txt