Metadata-Version: 1.0
Name: drf-irelation
Version: 0.0.1
Summary: Improved interaction with DRF relations.
Home-page: https://github.com/justjew/irelation
Author: justjew
Author-email: justjew1406@gmail.com
License: MIT
Keywords: django rest relation nested pk primary object
Platform: UNKNOWN
